[
    
    {
        "id": 0,
        "name": "helloKiti",
        "url": "helloKiti.png"
      },
      {
        "id": 1,
        "name": "helloKiti1",
        "url": "helloKiti1.png"
      },
      {
          "id": 2,
          "name": "helloKiti2",
        "url": "helloKiti2.png"
      },
      {
        "id": 3,
        "name": "helloKiti3",
        "url": "helloKiti3.png"
      },
      {
        "id": 4,
        "name": "helloKiti4",
        "url": "helloKiti4.png"
      },
      {
        "id": 5,
        "name": "unicorn",
        "url": "unicorn.png"
      },
      {
        "id": 6,
        "name": "unicorn1",
        "url": "unicorn1.png"
      },
      {
        "id": 7,
        "name": "unicorn2",
        "url": "unicorn2.png"
      },
      {
        "id": 8,
        "name": "unicorn3",
        "url": "unicorn3.png"
      },
      {
        "id": 9,
        "name": "unicorn4",
        "url": "unicorn4.png"
      },
      {
        "id": 10,
        "name": "firemanSam",
        "url": "firemanSam.png"
      },
      {
        "id": 11,
        "name": "firemanSam1",
        "url": "firemanSam1.png"
      },
      {
        "id": 12,
        "name": "firemanSam2",
        "url": "firemanSam2.png"
      },
      {
        "id": 13,
        "name": "firemanSam3",
        "url": "firemanSam3.png"
      },
      {
        "id": 14,
        "name": "firemanSam4",
        "url": "firemanSam4.png"
      }
]